docs/Makefile
docs/api_reference.rst
docs/conf.py
docs/contributing.rst
docs/history.rst
docs/index.rst
docs/make.bat
docs/pyfar.rst
docs/readme.rst
docs/classes/pyfar.audio.rst
docs/classes/pyfar.coordinates.rst
docs/classes/pyfar.filter.rst
docs/classes/pyfar.orientations.rst
docs/classes/pyfar.transmission_matrix.rst
docs/classes/resources/coordinate_systems.png
docs/modules/pyfar.dsp.fft.rst
docs/modules/pyfar.dsp.filter.rst
docs/modules/pyfar.dsp.rst
docs/modules/pyfar.io.rst
docs/modules/pyfar.plot.rst
docs/modules/pyfar.samplings.rst
docs/modules/pyfar.signals.files.rst
docs/modules/pyfar.signals.rst
docs/modules/pyfar.testing.plot_utils.rst
docs/modules/pyfar.testing.stub_utils.rst
docs/modules/pyfar.utils.rst
docs/resources/plot_shortcuts.rst
pyfar/__init__.py
pyfar/_utils.py
pyfar/utils.py
pyfar/classes/__init__.py
pyfar/classes/audio.py
pyfar/classes/coordinates.py
pyfar/classes/filter.py
pyfar/classes/orientations.py
pyfar/classes/transmission_matrix.py
pyfar/classes/warnings.py
pyfar/dsp/__init__.py
pyfar/dsp/dsp.py
pyfar/dsp/fft.py
pyfar/dsp/interpolation.py
pyfar/dsp/filter/__init__.py
pyfar/dsp/filter/_audiofilter.py
pyfar/dsp/filter/audiofilter.py
pyfar/dsp/filter/band_filter.py
pyfar/dsp/filter/fractional_octaves.py
pyfar/dsp/filter/gammatone.py
pyfar/io/__init__.py
pyfar/io/_codec.py
pyfar/io/io.py
pyfar/plot/__init__.py
pyfar/plot/_interaction.py
pyfar/plot/_line.py
pyfar/plot/_two_d.py
pyfar/plot/_utils.py
pyfar/plot/line.py
pyfar/plot/spatial.py
pyfar/plot/ticker.py
pyfar/plot/two_d.py
pyfar/plot/utils.py
pyfar/plot/plotstyles/dark.mplstyle
pyfar/plot/plotstyles/light.mplstyle
pyfar/plot/shortcuts/shortcuts.json
pyfar/samplings/__init__.py
pyfar/samplings/samplings.py
pyfar/samplings/spatial.py
pyfar/samplings/external/__init__.py
pyfar/samplings/external/eq_area_partitions.py
pyfar/samplings/external/samplings_fliege.mat
pyfar/samplings/external/samplings_lebedev.py
pyfar/signals/__init__.py
pyfar/signals/deterministic.py
pyfar-0.7.3.dist-info/licenses/LICENSE
pyfar-0.7.3.dist-info/METADATA
pyfar-0.7.3.dist-info/WHEEL
pyfar-0.7.3.dist-info/top_level.txt
pyfar-0.7.3.dist-info/RECORD
