Metadata-Version: 2.4
Name: pyfar
Version: 0.7.3
Summary: Project for data formats in acoustics.
Author-email: The pyfar developers <info@pyfar.org>
License: Copyright (c) [2020] [The pyfar developers]
Project-URL: Tracker, https://github.com/pyfar/pyfar/issues
Project-URL: Documentation, https://pyfar.readthedocs.io/
Project-URL: Download, https://pypi.org/project/pyfar/
Project-URL: Homepage, https://pyfar.org/
Project-URL: Source, https://github.com/pyfar/pyfar
Project-URL: Changelog, https://github.com/pyfar/pyfar/blob/main/HISTORY.rst
Keywords: pyfar,acoustics,Fourier transforms,audio signal processing,filterbanks,parametric filters,audio signal visualization,read and write audio signals
Classifier: Development Status :: 4 - Beta
Classifier: Intended Audience :: Science/Research
Classifier: License :: OSI Approved :: MIT License
Classifier: Natural Language :: English
Classifier: Programming Language :: Python :: 3
Classifier: Programming Language :: Python :: 3.9
Classifier: Programming Language :: Python :: 3.10
Classifier: Programming Language :: Python :: 3.11
Classifier: Programming Language :: Python :: 3.12
Requires-Python: >=3.9
License-File: LICENSE
Requires-Dist: numpy>=1.23.0
Requires-Dist: scipy>=1.5.0
Requires-Dist: matplotlib
Requires-Dist: sofar>=0.1.2
Requires-Dist: urllib3
Requires-Dist: deepdiff
Requires-Dist: soundfile>=0.11.0
Provides-Extra: deploy
Requires-Dist: twine; extra == "deploy"
Requires-Dist: wheel; extra == "deploy"
Requires-Dist: build; extra == "deploy"
Requires-Dist: setuptools; extra == "deploy"
Requires-Dist: bump-my-version; extra == "deploy"
Provides-Extra: tests
Requires-Dist: pytest; extra == "tests"
Requires-Dist: pytest-cov; extra == "tests"
Requires-Dist: watchdog; extra == "tests"
Requires-Dist: ruff==0.4.1; extra == "tests"
Requires-Dist: coverage; extra == "tests"
Provides-Extra: docs
Requires-Dist: sphinx; extra == "docs"
Requires-Dist: autodocsumm>=0.2.14; extra == "docs"
Requires-Dist: pydata-sphinx-theme; extra == "docs"
Requires-Dist: sphinx_mdinclude; extra == "docs"
Requires-Dist: sphinx-design; extra == "docs"
Requires-Dist: sphinx-favicon; extra == "docs"
Requires-Dist: sphinx-reredirects; extra == "docs"
Provides-Extra: dev
Requires-Dist: pyfar[deploy,docs,tests]; extra == "dev"
Dynamic: license-file
